{
  "updated": "2026-06-24T20:27:09.029242+00:00",
  "news": [
    {
      "title": "HDR10, HDR10+ ou Dolby Vision ? Décryptez les formats de votre TV pour sublimer les matchs nocturnes sans vous fatiguer les yeux",
      "link": "https://www.zdnet.fr/pratique/coupe-du-monde-2026-hdr10-hdr10-ou-dolby-vision-decryptez-les-formats-de-votre-tv-pour-sublimer-les-matchs-nocturnes-sans-vous-fatiguer-les-yeux-496824.htm#xtor=123456",
      "date": "mer, 24 Juin 2026 21:31:05 +0200",
      "source": "ZDNet FR",
      "fiabilite": "élevée",
      "sources_count": 3
    },
    {
      "title": "IA en entreprise : avant de lâcher les chevaux en déployant des agents d’IA, 4 conseils",
      "link": "https://www.zdnet.fr/pratique/ia-en-entreprise-avant-de-lacher-les-chevaux-en-deployant-des-agents-dintelligence-artificielle-4-facons-dagir-avec-une-extreme-prudence-497530.htm#xtor=123456",
      "date": "mer, 24 Juin 2026 16:30:52 +0200",
      "source": "ZDNet FR",
      "fiabilite": "élevée",
      "sources_count": 3
    },
    {
      "title": "Sony WH-1000XM6 vs. Sennheiser Momentum 5: après plusieurs mois de test, voici lequel de ces deux casques choisir",
      "link": "https://www.zdnet.fr/guide-achat/sony-wh-1000xm6-vs-sennheiser-momentum-5-apres-plusieurs-mois-de-test-voici-lequel-de-ces-deux-casques-choisir-497457.htm#xtor=123456",
      "date": "mar, 23 Juin 2026 22:23:07 +0200",
      "source": "ZDNet FR",
      "fiabilite": "élevée",
      "sources_count": 3
    },
    {
      "title": "J'ai modifié ces 5 paramètres de ma TV pour transfigurer l'image des matchs et éliminer le flou",
      "link": "https://www.zdnet.fr/pratique/coupe-du-monde-2026-jai-modifie-ces-5-parametres-de-ma-tv-pour-transfigurer-limage-des-matchs-et-eliminer-le-flou-496822.htm#xtor=123456",
      "date": "mar, 23 Juin 2026 22:15:17 +0200",
      "source": "ZDNet FR",
      "fiabilite": "élevée",
      "sources_count": 3
    },
    {
      "title": "IA en entreprise : 5 conseils pour automatiser les processus et mettre fin aux tracas liés à l'intégration des données",
      "link": "https://www.zdnet.fr/pratique/ia-en-entreprise-cinq-conseils-pour-automatiser-les-processus-et-mettre-fin-aux-tracas-lies-a-lintegration-des-donnees-497414.htm#xtor=123456",
      "date": "mar, 23 Juin 2026 16:01:47 +0200",
      "source": "ZDNet FR",
      "fiabilite": "élevée",
      "sources_count": 3
    },
    {
      "title": "60 Hz, 120 Hz ou 165 Hz ? Décryptez le taux de rafraîchissement de votre TV pour suivre le ballon sans aucun flou",
      "link": "https://www.zdnet.fr/pratique/coupe-du-monde-2026-60-hz-120-hz-ou-165-hz-decryptez-le-taux-de-rafraichissement-de-votre-tv-pour-suivre-le-ballon-sans-aucun-flou-496820.htm#xtor=123456",
      "date": "lun, 22 Juin 2026 22:00:36 +0200",
      "source": "ZDNet FR",
      "fiabilite": "élevée",
      "sources_count": 3
    },
    {
      "title": "Chez Mistral AI, l’OCR s’enrichit, mais cela a un prix",
      "link": "https://www.silicon.fr/data-ia-1372/mistral-ai-ocr-228004",
      "date": "Wed, 24 Jun 2026 12:20:32 +0000",
      "source": "Silicon.fr",
      "fiabilite": "élevée",
      "sources_count": 3
    },
    {
      "title": "Dopé aux microVM, Lambda se rapproche d’AgentCore",
      "link": "https://www.silicon.fr/data-ia-1372/aws-microvm-lambda-227992",
      "date": "Wed, 24 Jun 2026 08:23:26 +0000",
      "source": "Silicon.fr",
      "fiabilite": "élevée",
      "sources_count": 3
    },
    {
      "title": "Le RIPE NCC freine sa marche vers le cloud",
      "link": "https://www.silicon.fr/cloud-1370/le-ripe-ncc-freine-sa-marche-vers-le-cloud-227968",
      "date": "Wed, 24 Jun 2026 06:41:18 +0000",
      "source": "Silicon.fr",
      "fiabilite": "élevée",
      "sources_count": 3
    },
    {
      "title": "DevSecOps : la « plate-forme », une notion relative",
      "link": "https://www.silicon.fr/cloud-1370/devsecops-magic-quadrant-2026-227986",
      "date": "Tue, 23 Jun 2026 13:41:13 +0000",
      "source": "Silicon.fr",
      "fiabilite": "élevée",
      "sources_count": 3
    },
    {
      "title": "La pénurie de RAM ruisselle jusqu’à la DDR2",
      "link": "https://www.silicon.fr/business-1367/penurie-ram-ddr2-227979",
      "date": "Tue, 23 Jun 2026 08:57:49 +0000",
      "source": "Silicon.fr",
      "fiabilite": "élevée",
      "sources_count": 3
    },
    {
      "title": "De NetApp à Dell, changement d’échelle pour Guillaume de Landtsheer",
      "link": "https://www.silicon.fr/business-1367/guillaume-de-landtsheer-dell-227974",
      "date": "Tue, 23 Jun 2026 06:52:12 +0000",
      "source": "Silicon.fr",
      "fiabilite": "élevée",
      "sources_count": 3
    }
  ],
  "regul": []
}